{
  "Array": [
    "two-sum",
    "best-time-to-buy-and-sell-stock",
    "majority-element",
    "contains-duplicate",
    "maximum-subarray",
    "insert-interval",
    "3sum",
    "product-of-array-except-self",
    "combination-sum",
    "merge-intervals",
    "sort-colors",
    "container-with-most-water"
  ],
  "Stack": [
    "valid-parentheses",
    "implement-queue-using-stacks",
    "min-stack",
    "evaluate-reverse-polish-notation",
    "trapping-rain-water",
    "largest-rectangle-in-histogram",
    "daily-temperatures"
  ],
  "Linked List": [
    "merge-two-sorted-lists",
    "linked-list-cycle",
    "reverse-linked-list",
    "middle-of-the-linked-list",
    "lru-cache"
  ],
  "String": [
    "valid-palindrome",
    "valid-anagram",
    "longest-palindrome",
    "longest-substring-without-repeating-characters",
    "string-to-integer-atoi",
    "longest-palindromic-substring",
    "find-all-anagrams-in-a-string",
    "minimum-window-substring"
  ],
  "Binary Search": [
    "binary-search",
    "first-bad-version",
    "search-in-rotated-sorted-array",
    "time-based-key-value-store",
    "find-minimum-in-rotated-sorted-array",
    "maximum-profit-in-job-scheduling"
  ],
  "Tree": [
    "invert-binary-tree",
    "balanced-binary-tree",
    "lowest-common-ancestor-of-a-binary-search-tree",
    "binary-tree-level-order-traversal",
    "validate-binary-search-tree",
    "maximum-depth-of-binary-tree",
    "binary-tree-right-side-view",
    "construct-binary-tree-from-preorder-and-inorder-traversal",
    "serialize-and-deserialize-binary-tree",
    "kth-smallest-element-in-a-bst"
  ],
  "Graph": [
    "flood-fill",
    "01-matrix",
    "clone-graph",
    "course-schedule",
    "number-of-islands",
    "rotting-oranges",
    "accounts-merge",
    "word-ladder",
    "minimum-height-trees"
  ],
  "Dynamic Programming": [
    "climbing-stairs",
    "coin-change",
    "unique-paths",
    "word-break",
    "longest-increasing-subsequence",
    "partition-equal-subset-sum",
    "maximum-product-subarray"
  ],
  "Binary": [
    "add-binary",
    "counting-bits",
    "number-of-1-bits",
    "single-number",
    "missing-number"
  ],
  "Heap": [
    "k-closest-points-to-origin",
    "task-scheduler",
    "find-median-from-data-stream",
    "merge-k-sorted-lists",
    "top-k-frequent-elements"
  ],
  "Trie": [
    "implement-trie-prefix-tree",
    "word-search-ii"
  ],
  "Recursion": [
    "permutations",
    "subsets",
    "letter-combinations-of-a-phone-number"
  ],
  "Matrix": [
    "spiral-matrix",
    "set-matrix-zeroes",
    "rotate-image"
  ]
}